{
  "date": "2026-07-06",
  "rotation": "Weekly Escalation Rotation",
  "missions": [
    {
      "mission": "The Art Museum",
      "loot": "Ceska Vyroba S.R.O."
    },
    {
      "mission": "Manning National Zoo",
      "loot": "Golan Gear Ltd"
    },
    {
      "mission": "Camp White Oak",
      "loot": "Hard Wired"
    },
    {
      "mission": "The Pentagon",
      "loot": "Marksman Rifle"
    },
    {
      "mission": "DARPA Research Labs",
      "loot": "Sokolov Concern"
    }
  ],
  "vendor_caches": [
    {
      "type": "Weapons",
      "item": "MMRs"
    },
    {
      "type": "Gear",
      "item": "Backpacks"
    }
  ],
  "last_updated": "2026-07-06 10:01",
  "status": "ok",
  "fetched_at": "2026-07-06T22:47:07.221077+00:00"
}
